peppyproject/__init__.py
peppyproject/__main__.py
peppyproject/base.py
peppyproject/configuration.py
peppyproject/files.py
peppyproject/tables.py
peppyproject/tools/__init__.py
peppyproject/tools/base.py
peppyproject/tools/coverage.py
peppyproject/tools/flake8.py
peppyproject/tools/ruff.py
peppyproject/tools/setuptools.py
peppyproject/tools/setuptools_scm.py
peppyproject-1.0.2.dist-info/LICENSE
peppyproject-1.0.2.dist-info/METADATA
peppyproject-1.0.2.dist-info/WHEEL
peppyproject-1.0.2.dist-info/entry_points.txt
peppyproject-1.0.2.dist-info/top_level.txt
peppyproject-1.0.2.dist-info/RECORD
