Metadata-Version: 2.1
Name: peppyproject
Version: 1.0.2
Summary: create a PEP621-compliant `pyproject.toml` file from existing build configuration
Author: Zach Burnett
License: GNU GENERAL PUBLIC LICENSE
Project-URL: repository, https://github.com/zacharyburnett/peppyproject
Classifier: License :: OSI Approved :: GNU General Public License v3 (GPLv3)
Classifier: Operating System :: OS Independent
Classifier: Programming Language :: Python
Classifier: Programming Language :: Python :: 3 :: Only
Classifier: Programming Language :: Python :: 3.9
Classifier: Programming Language :: Python :: 3.10
Classifier: Programming Language :: Python :: 3.11
Requires-Python: >=3.9
License-File: LICENSE
Requires-Dist: ini2toml[full]
Requires-Dist: tomli >=2
Requires-Dist: tomli-w >=1
Requires-Dist: typepigeon >=2.0.1
Requires-Dist: typer
Provides-Extra: test
Requires-Dist: pytest ; extra == 'test'
Requires-Dist: tomli ; extra == 'test'
